codeCompletionCore/CodeCompletionCore.py
codeCompletionCore/__init__.py
odsllib-0.38.dist-info/METADATA
odsllib-0.38.dist-info/WHEEL
odsllib-0.38.dist-info/top_level.txt
odsllib-0.38.dist-info/RECORD
